docs/_config.yml
docs/index.md
docs/_layouts/default.html
docs/assets/funsize_engineer_card.png
funsize_engineer/__init__.py
funsize_engineer/__main__.py
funsize_engineer/_version.py
funsize_engineer/card.py
funsize_engineer/__pycache__/__init__.cpython-310.pyc
funsize_engineer/__pycache__/card.cpython-310.pyc
funsize_engineer/assets/ascii-art.txt
funsize_engineer/assets/calling_card_output.png
test_env/pyvenv.cfg
test_env/bin/Activate.ps1
test_env/bin/activate
test_env/bin/activate.csh
test_env/bin/activate.fish
test_env/bin/funsize-engineer
test_env/bin/markdown-it
test_env/bin/pip
test_env/bin/pip3
test_env/bin/pip3.10
test_env/bin/pygmentize
funsize_engineer-0.2.15.dist-info/METADATA
funsize_engineer-0.2.15.dist-info/WHEEL
funsize_engineer-0.2.15.dist-info/entry_points.txt
funsize_engineer-0.2.15.dist-info/top_level.txt
funsize_engineer-0.2.15.dist-info/RECORD
