Metadata-Version: 2.4
Name: funsize-engineer
Version: 0.2.15
Summary: A personal calling card for Jessica Rudd
Author-email: Jessica Rudd <jessica.rudd@fanduel.com>
License: MIT
Project-URL: Homepage, https://github.com/JessicaRudd/funsize-engineer
Project-URL: Repository, https://github.com/JessicaRudd/funsize-engineer
Classifier: Programming Language :: Python :: 3
Classifier: License :: OSI Approved :: MIT License
Classifier: Operating System :: OS Independent
Requires-Python: >=3.6
Requires-Dist: rich
